MANIFEST.in
README.rst
setup.py
ckeditor_staticfiles/__init__.py
ckeditor_staticfiles/static/ckeditor/CHANGES.md
ckeditor_staticfiles/static/ckeditor/LICENSE.md
ckeditor_staticfiles/static/ckeditor/README.md
ckeditor_staticfiles/static/ckeditor/build-config.js
ckeditor_staticfiles/static/ckeditor/ckeditor.js
ckeditor_staticfiles/static/ckeditor/config.js
ckeditor_staticfiles/static/ckeditor/contents.css
ckeditor_staticfiles/static/ckeditor/styles.js
ckeditor_staticfiles/static/ckeditor/adapters/jquery.js
ckeditor_staticfiles/static/ckeditor/lang/af.js
ckeditor_staticfiles/static/ckeditor/lang/ar.js
ckeditor_staticfiles/static/ckeditor/lang/bg.js
ckeditor_staticfiles/static/ckeditor/lang/bn.js
ckeditor_staticfiles/static/ckeditor/lang/bs.js
ckeditor_staticfiles/static/ckeditor/lang/ca.js
ckeditor_staticfiles/static/ckeditor/lang/cs.js
ckeditor_staticfiles/static/ckeditor/lang/cy.js
ckeditor_staticfiles/static/ckeditor/lang/da.js
ckeditor_staticfiles/static/ckeditor/lang/de.js
ckeditor_staticfiles/static/ckeditor/lang/el.js
ckeditor_staticfiles/static/ckeditor/lang/en-au.js
ckeditor_staticfiles/static/ckeditor/lang/en-ca.js
ckeditor_staticfiles/static/ckeditor/lang/en-gb.js
ckeditor_staticfiles/static/ckeditor/lang/en.js
ckeditor_staticfiles/static/ckeditor/lang/eo.js
ckeditor_staticfiles/static/ckeditor/lang/es.js
ckeditor_staticfiles/static/ckeditor/lang/et.js
ckeditor_staticfiles/static/ckeditor/lang/eu.js
ckeditor_staticfiles/static/ckeditor/lang/fa.js
ckeditor_staticfiles/static/ckeditor/lang/fi.js
ckeditor_staticfiles/static/ckeditor/lang/fo.js
ckeditor_staticfiles/static/ckeditor/lang/fr-ca.js
ckeditor_staticfiles/static/ckeditor/lang/fr.js
ckeditor_staticfiles/static/ckeditor/lang/gl.js
ckeditor_staticfiles/static/ckeditor/lang/gu.js
ckeditor_staticfiles/static/ckeditor/lang/he.js
ckeditor_staticfiles/static/ckeditor/lang/hi.js
ckeditor_staticfiles/static/ckeditor/lang/hr.js
ckeditor_staticfiles/static/ckeditor/lang/hu.js
django_ckeditor_staticfiles.egg-info/PKG-INFO
django_ckeditor_staticfiles.egg-info/SOURCES.txt
django_ckeditor_staticfiles.egg-info/dependency_links.txt
django_ckeditor_staticfiles.egg-info/top_level.txt